rosetta/__init__.py
rosetta/main.py
rosetta/core/__init__.py
rosetta/core/config.py
rosetta/core/exceptions.py
rosetta/models/__init__.py
rosetta/models/cell.py
rosetta/services/__init__.py
rosetta/services/extractor.py
rosetta/services/translation_service.py
rosetta/services/translator.py
rosetta_xl-0.1.0.dist-info/METADATA
rosetta_xl-0.1.0.dist-info/WHEEL
rosetta_xl-0.1.0.dist-info/entry_points.txt
rosetta_xl-0.1.0.dist-info/licenses/LICENSE
rosetta_xl-0.1.0.dist-info/RECORD
