Metadata-Version: 2.4
Name: rosetta-xl
Version: 0.1.0
Summary: AI-powered Excel translation tool that preserves formatting, formulas, and data integrity
Project-URL: Homepage, https://github.com/ewalid/rosetta
Project-URL: Repository, https://github.com/ewalid/rosetta
Project-URL: Issues, https://github.com/ewalid/rosetta/issues
Author-email: Walid Elmselmi <ewalid@example.com>
License: MIT
License-File: LICENSE
Keywords: ai,claude,excel,i18n,localization,translation,xlsx
Classifier: Development Status :: 4 - Beta
Classifier: Environment :: Console
Classifier: Intended Audience :: Developers
Classifier: Intended Audience :: End Users/Desktop
Classifier: License :: OSI Approved :: MIT License
Classifier: Operating System :: OS Independent
Classifier: Programming Language :: Python :: 3
Classifier: Programming Language :: Python :: 3.11
Classifier: Programming Language :: Python :: 3.12
Classifier: Topic :: Office/Business :: Office Suites
Classifier: Topic :: Text Processing :: Linguistic
Requires-Python: >=3.11
Requires-Dist: anthropic>=0.39.0
Requires-Dist: click>=8.1.7
Requires-Dist: openpyxl>=3.1.5
Requires-Dist: python-dotenv>=1.0.0
Provides-Extra: dev
Requires-Dist: black>=24.0.0; extra == 'dev'
Requires-Dist: fastapi>=0.115.0; extra == 'dev'
Requires-Dist: httpx>=0.27.0; extra == 'dev'
Requires-Dist: mypy>=1.11.0; extra == 'dev'
Requires-Dist: pytest-asyncio>=0.24.0; extra == 'dev'
Requires-Dist: pytest-cov>=4.1.0; extra == 'dev'
Requires-Dist: pytest>=8.0.0; extra == 'dev'
Requires-Dist: python-multipart>=0.0.12; extra == 'dev'
Requires-Dist: ruff>=0.6.0; extra == 'dev'
Requires-Dist: uvicorn>=0.32.0; extra == 'dev'
